dqx_network_checks/__init__.py
dqx_network_checks/checks.py
dqx_network_checks/validators.py
dqx_network_checks-0.1.0.dist-info/METADATA
dqx_network_checks-0.1.0.dist-info/WHEEL
dqx_network_checks-0.1.0.dist-info/licenses/LICENSE
dqx_network_checks-0.1.0.dist-info/RECORD
