Metadata-Version: 2.4
Name: dqx-network-checks
Version: 0.1.0
Summary: Network checks for the DQX data quality framework
Author-email: Tim Dikland <timdikland@gmail.com>
License-File: LICENSE
Requires-Python: >=3.11
Requires-Dist: databricks-labs-dqx~=0.6.0
Requires-Dist: pyspark~=3.5.0
